MANIFEST.in
README.rst
setup.py
tweetypy/__init__.py
tweetypy/actions.yaml
tweetypy/config.py
tweetypy/config.yaml
tweetypy/icons.yaml
tweetypy/mainwin.py
tweetypy/menu.yaml
tweetypy/spectrogram.py
tweetypy.egg-info/PKG-INFO
tweetypy.egg-info/SOURCES.txt
tweetypy.egg-info/dependency_links.txt
tweetypy.egg-info/entry_points.txt
tweetypy.egg-info/not-zip-safe
tweetypy.egg-info/requires.txt
tweetypy.egg-info/top_level.txt