Metadata-Version: 1.2
Name: tweetypy
Version: 1.0.0rc6
Summary: Bird song analysis tools
Home-page: http://jessemcclure.org
Author: Jesse McClure
Author-email: jmcclure@broadinstitute.org
License: MIT
Platform: UNKNOWN
Classifier: Development Status :: 3 - Alpha
Classifier: License :: OSI Approved :: MIT License
Classifier: Intended Audience :: Science/Research
Classifier: Programming Language :: Python :: 3
Classifier: Topic :: Multimedia :: Sound/Audio :: Analysis
Classifier: Topic :: Scientific/Engineering :: Visualization
Requires-Python: >=3
